{"title":"Discovery.Channel.How.Its.Made.Cine.Cameras.PDTV.XviD-CiRCLE","uid":4833297,"size":182713478,"categoryP":"video","categoryS":"tv_shows","magnet":"?xt=urn:btih:14ee80b30991ff8dd3e5486f420d5fb1026bc06e&amp;dn=Discovery.Channel.How.Its.Made.Cine.Cameras.PDTV.XviD-CiRCLE&amp;tr=udp%3A%2F%2Ftracker.openbittorrent.com%3A80&amp;tr=udp%3A%2F%2Fopen.demonii.com%3A1337&amp;tr=udp%3A%2F%2Ftracker.coppersurfer.tk%3A6969&amp;tr=udp%3A%2F%2Fexodus.desync.com%3A6969","seeders":0,"leechers":1,"uploader":"budakrist","files":2,"time":1239216343,"description":"From NFO:                           \n                                                                                     \n              Release Date .......: 05-04-2009               \n              Air Date ...........: 05-04-2009\n              Language ...........: English        \n              Runtime ............: 21m29s      \n              Genre ..............: Docu        \n              Source .............: Digital Sat     \n              Aspect Ratio .......: 1.333 512x2884\n              Video Info .........: .avi @ 991 kb/s\n              Framerate ..........: 25.000\n              Audio Info .........: vbr ac3 @ 129 kb/s\n              Subs ...............: none\n              Extra ..............: none\n \n\n--------\n\nI like to upload shows that are hard to find and not uploaded by anyone else. I also upload a lot of Late night talk shows\n\nCheck  &lt;a href=&quot;\nhttp://thepiratebay.se/user/budakrist&quot; rel=&quot;nofollow&quot; target=&quot;_NEW&quot;&gt;\nhttp://thepiratebay.se/user/budakrist&lt;/a&gt; \nto see what else I've seeded.\n\nEnjoy, and try to seed something of your own it's easy.","torrent":{"xt":"urn:btih:14ee80b30991ff8dd3e5486f420d5fb1026bc06e","amp;dn":"Discovery.Channel.How.Its.Made.Cine.Cameras.PDTV.XviD-CiRCLE","amp;tr":["udp%3A%2F%2Ftracker.openbittorrent.com%3A80","udp%3A%2F%2Fopen.demonii.com%3A1337","udp%3A%2F%2Ftracker.coppersurfer.tk%3A6969","udp%3A%2F%2Fexodus.desync.com%3A6969"],"infoHash":"14ee80b30991ff8dd3e5486f420d5fb1026bc06e","infoHashBuffer":{"type":"Buffer","data":[20,238,128,179,9,145,255,141,211,229,72,111,66,13,95,177,2,107,192,110]},"announce":[],"urlList":[]}}