{"title":"Miho Tsujii Life Insurance Occupational 14","uid":6752784,"size":1010808399,"categoryP":"porn","categoryS":"movies","magnet":"?xt=urn:btih:15d756a438f4f5398a4c88989d4d69e5241bd43d&amp;dn=Miho+Tsujii+Life+Insurance+Occupational+14&amp;tr=udp%3A%2F%2Ftracker.openbittorrent.com%3A80&amp;tr=udp%3A%2F%2Fopen.demonii.com%3A1337&amp;tr=udp%3A%2F%2Ftracker.coppersurfer.tk%3A6969&amp;tr=udp%3A%2F%2Fexodus.desync.com%3A6969","seeders":0,"leechers":3,"uploader":"exmnova","files":3,"time":1318935835,"description":"Miho Tsujii\nLife Insurance Occupational 14\n\n &lt;a href=&quot;\nhttp://0.picswan.com/show.php/21443_2.jpg.html&quot; rel=&quot;nofollow&quot; target=&quot;_NEW&quot;&gt;\nhttp://0.picswan.com/show.php/21443_2.jpg.html&lt;/a&gt;\n &lt;a href=&quot;\nhttp://0.picswan.com/show.php/21442_1.jpg.html&quot; rel=&quot;nofollow&quot; target=&quot;_NEW&quot;&gt;\nhttp://0.picswan.com/show.php/21442_1.jpg.html&lt;/a&gt;\n","torrent":{"xt":"urn:btih:15d756a438f4f5398a4c88989d4d69e5241bd43d","amp;dn":"Miho+Tsujii+Life+Insurance+Occupational+14","amp;tr":["udp%3A%2F%2Ftracker.openbittorrent.com%3A80","udp%3A%2F%2Fopen.demonii.com%3A1337","udp%3A%2F%2Ftracker.coppersurfer.tk%3A6969","udp%3A%2F%2Fexodus.desync.com%3A6969"],"infoHash":"15d756a438f4f5398a4c88989d4d69e5241bd43d","infoHashBuffer":{"type":"Buffer","data":[21,215,86,164,56,244,245,57,138,76,136,152,157,77,105,229,36,27,212,61]},"announce":[],"urlList":[]}}