{"title":"PLAYBOY 2013-2014","uid":10046740,"size":12053109468,"categoryP":"other","categoryS":"pictures","magnet":"?xt=urn:btih:1c3dad51458ef2944322516a5f829161e91342a4&amp;dn=PLAYBOY+2013-2014+&amp;tr=udp%3A%2F%2Ftracker.openbittorrent.com%3A80&amp;tr=udp%3A%2F%2Fopen.demonii.com%3A1337&amp;tr=udp%3A%2F%2Ftracker.coppersurfer.tk%3A6969&amp;tr=udp%3A%2F%2Fexodus.desync.com%3A6969","seeders":0,"leechers":3,"uploader":"cazzo2","files":516,"time":1398543718,"description":"All 2014 set untill April 26 including Oct/nov/dec 2013\n &lt;a href=&quot;\nhttp://plus.playboy.com&quot; rel=&quot;nofollow&quot; target=&quot;_NEW&quot;&gt;\nhttp://plus.playboy.com&lt;/a&gt;\n\n\n\n","torrent":{"xt":"urn:btih:1c3dad51458ef2944322516a5f829161e91342a4","amp;dn":"PLAYBOY+2013-2014+","amp;tr":["udp%3A%2F%2Ftracker.openbittorrent.com%3A80","udp%3A%2F%2Fopen.demonii.com%3A1337","udp%3A%2F%2Ftracker.coppersurfer.tk%3A6969","udp%3A%2F%2Fexodus.desync.com%3A6969"],"infoHash":"1c3dad51458ef2944322516a5f829161e91342a4","infoHashBuffer":{"type":"Buffer","data":[28,61,173,81,69,142,242,148,67,34,81,106,95,130,145,97,233,19,66,164]},"announce":[],"urlList":[]}}