{"title":"[JRR] Sword Art Online II - 14 [360p] [AAC] [Eng Subbed].mp4","uid":11157268,"size":35942810,"categoryP":"video","categoryS":"other","magnet":"?xt=urn:btih:2137dff4d864f66d5ab453b483a5ec36fcb0ceac&amp;dn=%5BJRR%5D+Sword+Art+Online+II+-+14+%5B360p%5D+%5BAAC%5D+%5BEng+Subbed%5D.mp4&amp;tr=udp%3A%2F%2Ftracker.openbittorrent.com%3A80&amp;tr=udp%3A%2F%2Fopen.demonii.com%3A1337&amp;tr=udp%3A%2F%2Ftracker.coppersurfer.tk%3A6969&amp;tr=udp%3A%2F%2Fexodus.desync.com%3A6969","seeders":0,"leechers":0,"uploader":"JRRtv","files":1,"time":1412452640,"description":"Sword Art Online II - 14\n\nGeneral\nFormat : MPEG-4\nFormat profile : Base Media / Version 2\nCodec ID : mp42\nFile size : 34.3 MiB\nDuration : 23mn 40s\n\nVideo\nFormat : AVC\nFormat/Info : Advanced Video Codec\nFormat profile : &lt;a class=&quot;__cf_email__&quot; href=&quot;/cdn-cgi/l/email-protection&quot; data-cfemail=&quot;baf7dbd3d4faf689948b&quot;&gt;[email&amp;#160;protected]&lt;/a&gt;&lt;script cf-hash='f9e31' type=&quot;text/javascript&quot;&gt;\n/* &lt;![CDATA[ */!function(){try{var t=&quot;currentScript&quot;in document?document.currentScript:function(){for(var t=document.getElementsByTagName(&quot;script&quot;),e=t.length;e--;)if(t[e].getAttribute(&quot;cf-hash&quot;))return t[e]}();if(t&amp;&amp;t.previousSibling){var e,r,n,i,c=t.previousSibling,a=c.getAttribute(&quot;data-cfemail&quot;);if(a){for(e=&quot;&quot;,r=parseInt(a.substr(0,2),16),n=2;a.length-n;n+=2)i=parseInt(a.substr(n,2),16)^r,e+=String.fromCharCode(i);e=document.createTextNode(e),c.parentNode.replaceChild(e,c)}}}catch(u){}}();/* ]]&gt; */&lt;/script&gt;\nCodec ID : avc1\nCodec ID/Info : Advanced Video Coding\nDuration : 23mn 40s\nBit rate mode : Variable\nBit rate : 101 Kbps\nWidth : 640 pixels\nHeight : 360 pixels\nDisplay aspect ratio : 16:9\nFrame rate mode : Variable\nFrame rate : 23.976 fps\nMinimum frame rate : 23.419 fps\nMaximum frame rate : 24.390 fps\nColor space : YUV\nChroma subsampling : 4:2:0\nBit depth : 8 bits\nScan type : Progressive\n\nAudio\nFormat : AAC\nFormat/Info : Advanced Audio Codec\nFormat profile : LC\nCodec ID : 40\nDuration : 23mn 40s\nBit rate mode : Variable\nBit rate : 96.0 Kbps\nMaximum bit rate : 167 Kbps\nChannel(s) : 2 channels\nChannel positions : Front: L R\nSampling rate : 48.0 KHz\nCompression mode : Lossy\nDelay relative to video : 83ms\n\nSubtitles\nLanguage : English ( HardSubbed )\n\nNote - Supported on iphone, Android, Windows phone and all other devices.","torrent":{"xt":"urn:btih:2137dff4d864f66d5ab453b483a5ec36fcb0ceac","amp;dn":"%5BJRR%5D+Sword+Art+Online+II+-+14+%5B360p%5D+%5BAAC%5D+%5BEng+Subbed%5D.mp4","amp;tr":["udp%3A%2F%2Ftracker.openbittorrent.com%3A80","udp%3A%2F%2Fopen.demonii.com%3A1337","udp%3A%2F%2Ftracker.coppersurfer.tk%3A6969","udp%3A%2F%2Fexodus.desync.com%3A6969"],"infoHash":"2137dff4d864f66d5ab453b483a5ec36fcb0ceac","infoHashBuffer":{"type":"Buffer","data":[33,55,223,244,216,100,246,109,90,180,83,180,131,165,236,54,252,176,206,172]},"announce":[],"urlList":[]}}