{"title":"CXAZ-022 Fukumoto Misae, Matsumoto Marina, Otsuki Hibiki JAV CEN","uid":9794831,"size":3272328537,"categoryP":"porn","categoryS":"movie_clips","magnet":"?xt=urn:btih:214574bfe7af870180f0e98bdd17b358d844e4a3&amp;dn=CXAZ-022+Fukumoto+Misae%2C+Matsumoto+Marina%2C+Otsuki+Hibiki+JAV+CEN&amp;tr=udp%3A%2F%2Ftracker.openbittorrent.com%3A80&amp;tr=udp%3A%2F%2Fopen.demonii.com%3A1337&amp;tr=udp%3A%2F%2Ftracker.coppersurfer.tk%3A6969&amp;tr=udp%3A%2F%2Fexodus.desync.com%3A6969","seeders":0,"leechers":5,"uploader":"3xplanet","files":1,"time":1395295591,"description":"CXAZ-022 Fukumoto Misae, Matsumoto Marina, Otsuki Hibiki JAV CENSORED\nCover &lt;a href=&quot;\nhttp://www.3xplanet.com/view/33347.html&quot; rel=&quot;nofollow&quot; target=&quot;_NEW&quot;&gt;\nhttp://www.3xplanet.com/view/33347.html&lt;/a&gt;\nScreenshot &lt;a href=&quot;\nhttp://www.3xplanet.com/view/33458.html&quot; rel=&quot;nofollow&quot; target=&quot;_NEW&quot;&gt;\nhttp://www.3xplanet.com/view/33458.html&lt;/a&gt;\nTitle: \nStarring: Fukumoto Misae, Matsumoto Marina, Otsuki Hibiki\nStudio:  Llanes\n\nTag: JAV, CENSORED, Llanes, Mature, lesbian, cunnilingus\n\n","torrent":{"xt":"urn:btih:214574bfe7af870180f0e98bdd17b358d844e4a3","amp;dn":"CXAZ-022+Fukumoto+Misae%2C+Matsumoto+Marina%2C+Otsuki+Hibiki+JAV+CEN","amp;tr":["udp%3A%2F%2Ftracker.openbittorrent.com%3A80","udp%3A%2F%2Fopen.demonii.com%3A1337","udp%3A%2F%2Ftracker.coppersurfer.tk%3A6969","udp%3A%2F%2Fexodus.desync.com%3A6969"],"infoHash":"214574bfe7af870180f0e98bdd17b358d844e4a3","infoHashBuffer":{"type":"Buffer","data":[33,69,116,191,231,175,135,1,128,240,233,139,221,23,179,88,216,68,228,163]},"announce":[],"urlList":[]}}