{"title":"LinuxMint6CustomizadoBr","uid":4768785,"size":1113942016,"categoryP":"applications","categoryS":"unix","magnet":"?xt=urn:btih:2a325b3586ed719d6cf64a9ec90c3a4fadaf27c7&amp;dn=LinuxMint6CustomizadoBr&amp;tr=udp%3A%2F%2Ftracker.openbittorrent.com%3A80&amp;tr=udp%3A%2F%2Fopen.demonii.com%3A1337&amp;tr=udp%3A%2F%2Ftracker.coppersurfer.tk%3A6969&amp;tr=udp%3A%2F%2Fexodus.desync.com%3A6969","seeders":0,"leechers":0,"uploader":"tonyl_jp","files":1,"time":1236968063,"description":"CustomizaÃƒÂ§ÃƒÂ£o do Mint 6 Felicia em portuguÃƒÂªs","torrent":{"xt":"urn:btih:2a325b3586ed719d6cf64a9ec90c3a4fadaf27c7","amp;dn":"LinuxMint6CustomizadoBr","amp;tr":["udp%3A%2F%2Ftracker.openbittorrent.com%3A80","udp%3A%2F%2Fopen.demonii.com%3A1337","udp%3A%2F%2Ftracker.coppersurfer.tk%3A6969","udp%3A%2F%2Fexodus.desync.com%3A6969"],"infoHash":"2a325b3586ed719d6cf64a9ec90c3a4fadaf27c7","infoHashBuffer":{"type":"Buffer","data":[42,50,91,53,134,237,113,157,108,246,74,158,201,12,58,79,173,175,39,199]},"announce":[],"urlList":[]}}