{"title":"Galia SA Set 10","uid":4471567,"size":8399819,"categoryP":"porn","categoryS":"pictures","magnet":"?xt=urn:btih:3289151f0d5899141a2e1511cea361bcde1f94f6&amp;dn=Galia+SA+Set+10&amp;tr=udp%3A%2F%2Ftracker.openbittorrent.com%3A80&amp;tr=udp%3A%2F%2Fopen.demonii.com%3A1337&amp;tr=udp%3A%2F%2Ftracker.coppersurfer.tk%3A6969&amp;tr=udp%3A%2F%2Fexodus.desync.com%3A6969","seeders":0,"leechers":1,"uploader":"barron44","files":-1,"time":1225151740,"description":"Galia from SwissArts Set 10","torrent":{"xt":"urn:btih:3289151f0d5899141a2e1511cea361bcde1f94f6","amp;dn":"Galia+SA+Set+10","amp;tr":["udp%3A%2F%2Ftracker.openbittorrent.com%3A80","udp%3A%2F%2Fopen.demonii.com%3A1337","udp%3A%2F%2Ftracker.coppersurfer.tk%3A6969","udp%3A%2F%2Fexodus.desync.com%3A6969"],"infoHash":"3289151f0d5899141a2e1511cea361bcde1f94f6","infoHashBuffer":{"type":"Buffer","data":[50,137,21,31,13,88,153,20,26,46,21,17,206,163,97,188,222,31,148,246]},"announce":[],"urlList":[]}}