{"title":"350 Super Hot Girls Wallpapers [Overload]","uid":6781968,"size":268996734,"categoryP":"other","categoryS":"pictures","magnet":"?xt=urn:btih:34c747730dc3e1dadb133baf8a561f44a8f72709&amp;dn=350+Super+Hot+Girls+Wallpapers+%5BOverload%5D&amp;tr=udp%3A%2F%2Ftracker.openbittorrent.com%3A80&amp;tr=udp%3A%2F%2Fopen.demonii.com%3A1337&amp;tr=udp%3A%2F%2Ftracker.coppersurfer.tk%3A6969&amp;tr=udp%3A%2F%2Fexodus.desync.com%3A6969","seeders":0,"leechers":0,"uploader":null,"files":353,"time":1319934654,"description":"350 Super Hot Girls Wallpapers [Overload]\n\nNice set around 350jpg \n\nwant more then visit us here at our new address.. \n &lt;a href=&quot;\nhttp://overloadextreme.tk/home/index.php&quot; rel=&quot;nofollow&quot; target=&quot;_NEW&quot;&gt;\nhttp://overloadextreme.tk/home/index.php&lt;/a&gt;\n\nenjoy","torrent":{"xt":"urn:btih:34c747730dc3e1dadb133baf8a561f44a8f72709","amp;dn":"350+Super+Hot+Girls+Wallpapers+%5BOverload%5D","amp;tr":["udp%3A%2F%2Ftracker.openbittorrent.com%3A80","udp%3A%2F%2Fopen.demonii.com%3A1337","udp%3A%2F%2Ftracker.coppersurfer.tk%3A6969","udp%3A%2F%2Fexodus.desync.com%3A6969"],"infoHash":"34c747730dc3e1dadb133baf8a561f44a8f72709","infoHashBuffer":{"type":"Buffer","data":[52,199,71,115,13,195,225,218,219,19,59,175,138,86,31,68,168,247,39,9]},"announce":[],"urlList":[]}}