{"title":"City.Island.2009.480p.BRRip.XviD.AC3-LEGi0N","uid":5602835,"size":1471683564,"categoryP":"video","categoryS":"movies","magnet":"?xt=urn:btih:41fac1fe7aa43475ba420d2a11a6fb2462636d57&amp;dn=City.Island.2009.480p.BRRip.XviD.AC3-LEGi0N&amp;tr=udp%3A%2F%2Ftracker.openbittorrent.com%3A80&amp;tr=udp%3A%2F%2Fopen.demonii.com%3A1337&amp;tr=udp%3A%2F%2Ftracker.coppersurfer.tk%3A6969&amp;tr=udp%3A%2F%2Fexodus.desync.com%3A6969","seeders":0,"leechers":0,"uploader":"TvTeam","files":3,"time":1275407130,"description":". \n \n &lt;a href=&quot;\nhttp://www.torrentday.com&quot; rel=&quot;nofollow&quot; target=&quot;_NEW&quot;&gt;\nhttp://www.torrentday.com&lt;/a&gt; :  Your Key To The Scene.\n\n\nNow TvTeam with [No-RAR] Releases.\n\n\n\n(((((((((((((= Enjoy No RAR releases =))))))))))))))))))))\n\n\n\n...................................NFO:....................................\n\n.","torrent":{"xt":"urn:btih:41fac1fe7aa43475ba420d2a11a6fb2462636d57","amp;dn":"City.Island.2009.480p.BRRip.XviD.AC3-LEGi0N","amp;tr":["udp%3A%2F%2Ftracker.openbittorrent.com%3A80","udp%3A%2F%2Fopen.demonii.com%3A1337","udp%3A%2F%2Ftracker.coppersurfer.tk%3A6969","udp%3A%2F%2Fexodus.desync.com%3A6969"],"infoHash":"41fac1fe7aa43475ba420d2a11a6fb2462636d57","infoHashBuffer":{"type":"Buffer","data":[65,250,193,254,122,164,52,117,186,66,13,42,17,166,251,36,98,99,109,87]},"announce":[],"urlList":[]}}