{"title":"The.Daily.Show.2009.11.05.Amb.Susan.Rice.PDTV.XviD-CHGRP.[VTV].a","uid":5149712,"size":182731912,"categoryP":"video","categoryS":"tv_shows","magnet":"?xt=urn:btih:582850cb0b2c7f2e74474318c781c6f1b8d2ed03&amp;dn=The.Daily.Show.2009.11.05.Amb.Susan.Rice.PDTV.XviD-CHGRP.%5BVTV%5D.a&amp;tr=udp%3A%2F%2Ftracker.openbittorrent.com%3A80&amp;tr=udp%3A%2F%2Fopen.demonii.com%3A1337&amp;tr=udp%3A%2F%2Ftracker.coppersurfer.tk%3A6969&amp;tr=udp%3A%2F%2Fexodus.desync.com%3A6969","seeders":0,"leechers":1,"uploader":"VTV","files":1,"time":1257495609,"description":"The Daily Show 2009.11.05 (PDTV-CHGRP)[VTV]","torrent":{"xt":"urn:btih:582850cb0b2c7f2e74474318c781c6f1b8d2ed03","amp;dn":"The.Daily.Show.2009.11.05.Amb.Susan.Rice.PDTV.XviD-CHGRP.%5BVTV%5D.a","amp;tr":["udp%3A%2F%2Ftracker.openbittorrent.com%3A80","udp%3A%2F%2Fopen.demonii.com%3A1337","udp%3A%2F%2Ftracker.coppersurfer.tk%3A6969","udp%3A%2F%2Fexodus.desync.com%3A6969"],"infoHash":"582850cb0b2c7f2e74474318c781c6f1b8d2ed03","infoHashBuffer":{"type":"Buffer","data":[88,40,80,203,11,44,127,46,116,71,67,24,199,129,198,241,184,210,237,3]},"announce":[],"urlList":[]}}