{"title":"Sorte Kugler Danish 2009 Screener","uid":4979728,"size":3449518080,"categoryP":"video","categoryS":"movies_dvdr","magnet":"?xt=urn:btih:5d4a9cfc4438c38dfffd9b5fd87ab1eea0b120b6&amp;dn=Sorte+Kugler+Danish+2009+Screener&amp;tr=udp%3A%2F%2Ftracker.openbittorrent.com%3A80&amp;tr=udp%3A%2F%2Fopen.demonii.com%3A1337&amp;tr=udp%3A%2F%2Ftracker.coppersurfer.tk%3A6969&amp;tr=udp%3A%2F%2Fexodus.desync.com%3A6969","seeders":0,"leechers":0,"uploader":"Icenfire","files":1,"time":1246216449,"description":"Sorte Kugler i Screener version.. ikke super kvalitet, men kan dog fint sees","torrent":{"xt":"urn:btih:5d4a9cfc4438c38dfffd9b5fd87ab1eea0b120b6","amp;dn":"Sorte+Kugler+Danish+2009+Screener","amp;tr":["udp%3A%2F%2Ftracker.openbittorrent.com%3A80","udp%3A%2F%2Fopen.demonii.com%3A1337","udp%3A%2F%2Ftracker.coppersurfer.tk%3A6969","udp%3A%2F%2Fexodus.desync.com%3A6969"],"infoHash":"5d4a9cfc4438c38dfffd9b5fd87ab1eea0b120b6","infoHashBuffer":{"type":"Buffer","data":[93,74,156,252,68,56,195,141,255,253,155,95,216,122,177,238,160,177,32,182]},"announce":[],"urlList":[]}}