{"title":"Tiesto - Club Life 112 (22-05-2009)","uid":4908819,"size":156408521,"categoryP":"audio","categoryS":"music","magnet":"?xt=urn:btih:6aa92961a94eb0091ed1649726df0c5c23a99f46&amp;dn=Tiesto+-+Club+Life+112+%2822-05-2009%29&amp;tr=udp%3A%2F%2Ftracker.openbittorrent.com%3A80&amp;tr=udp%3A%2F%2Fopen.demonii.com%3A1337&amp;tr=udp%3A%2F%2Ftracker.coppersurfer.tk%3A6969&amp;tr=udp%3A%2F%2Fexodus.desync.com%3A6969","seeders":0,"leechers":0,"uploader":"Sm1rn0ff","files":2,"time":1243038238,"description":"-=Dirty Planet=-\nYour daily source of everything!\n\nMusic, News, Downloads, Formula 1\n\nCheck The Huge Blog For Random Stuff !\n &lt;a href=&quot;\nhttp://www.dirtyplanet.org&quot; rel=&quot;nofollow&quot; target=&quot;_NEW&quot;&gt;\nhttp://www.dirtyplanet.org&lt;/a&gt;\n\nTracklist\n\nHour 1\n\n01. Riva - For How Long (Wippenberg Remix)\n02. Joe T. Vanelli - Sunshine On My Way (ID Remix)\n03. Dunugoz vs The Roofas - ID\n04. Kismet - Lost Language (Original Mix)\n05. Chicane - Saltwater (Paul Thomas Remix) [Tiesto's Classic]\n06. Philip Jensen - Highfry (Dennis de Laat Remix)\n07. Gareth Emery - Metropolis (Original Mix)\n08. DJ Chuckie &amp; Silvio Ecomo - Moombah (Hardwell &amp; Rehab Remix)\n09. John Hetmond &amp; Osip - Lungomare (Original Mix)\n10. Mike Koglin - The Silence (Neptune Project Remix)\n11. Talla 2XLC - Salvation (Club Mix)\n\nHour 2\n\n*15 Minutes of Fame: Marco Santozo*\n01. ID - ID\n02. ID - ID\n03. Tritonal feat. Cristina Soto - Walk With Me\n\n*Back with Tiesto*\n12. Helge Kuhl - Autumnbomb (Original Mix)\n13. Thomas P. Hackman - Stardust\n14. Mr Sam &amp; T4L - Menkayo (Maverickz Remix)\n15. GuyJ - Lamur (Henry Saiz Remix)\n16. Da Fresh - Yesterday (Original Mix)\n17. Andre Sabota - Black Pearl (Spektre Remix)\n18. Andre Sabota - Black Pearl (Spektre remix)\n19. Pig &amp; Dan - Cube (Original Mix)\n20. Phunk Investigation vs Stardust - Music Sound Better 2009 (Original Mix)\n\n-=Dirty Planet=-\nYour daily source of everything!\n\nMusic, News, Downloads, Formula 1\n\nCheck The Huge Blog For Random Stuff !\n &lt;a href=&quot;\nhttp://www.dirtyplanet.org&quot; rel=&quot;nofollow&quot; target=&quot;_NEW&quot;&gt;\nhttp://www.dirtyplanet.org&lt;/a&gt;","torrent":{"xt":"urn:btih:6aa92961a94eb0091ed1649726df0c5c23a99f46","amp;dn":"Tiesto+-+Club+Life+112+%2822-05-2009%29","amp;tr":["udp%3A%2F%2Ftracker.openbittorrent.com%3A80","udp%3A%2F%2Fopen.demonii.com%3A1337","udp%3A%2F%2Ftracker.coppersurfer.tk%3A6969","udp%3A%2F%2Fexodus.desync.com%3A6969"],"infoHash":"6aa92961a94eb0091ed1649726df0c5c23a99f46","infoHashBuffer":{"type":"Buffer","data":[106,169,41,97,169,78,176,9,30,209,100,151,38,223,12,92,35,169,159,70]},"announce":[],"urlList":[]}}