{"title":"Hamtaro.och.ham.ham.klubbhuset.swedish.ispy100fib","uid":6007313,"size":1233760260,"categoryP":"video","categoryS":"movies","magnet":"?xt=urn:btih:7198de6a943c7d43d1d4071aba7ae121ac3efaf9&amp;dn=Hamtaro.och.ham.ham.klubbhuset.swedish.ispy100fib&amp;tr=udp%3A%2F%2Ftracker.openbittorrent.com%3A80&amp;tr=udp%3A%2F%2Fopen.demonii.com%3A1337&amp;tr=udp%3A%2F%2Ftracker.coppersurfer.tk%3A6969&amp;tr=udp%3A%2F%2Fexodus.desync.com%3A6969","seeders":0,"leechers":1,"uploader":"ispy100fib","files":1,"time":1291358633,"description":"Alla talar svenska.\n\n\n\n\nHAMTARO Den nyfikne hamstern Hamtaro har tillsammans med sin ÃƒÂ¤gare Laura och hennes familj flyttat till en ny stad. HÃƒÂ¤r ska bÃƒÂ¥da tvÃƒÂ¥ hitta nya kompisar och det drÃƒÂ¶jer inte lÃƒÂ¤nge fÃƒÂ¶rrÃƒÂ¤n Hamtaro tagit sig ner via stuprÃƒÂ¶ret och ÃƒÂ¤r ute pÃƒÂ¥ nya ÃƒÂ¤ventyr. HÃƒÂ¤r mÃƒÂ¶ter han sin hamstergranne Oxnard, och tillsammans rÃƒÂ¥kar de ramla de ner i en djup hÃƒÂ¥la, dÃƒÂ¤r hamstergangstern Boss och den vackra Bijou gÃƒÂ¶mmer sig ... HAM-HAM-KLUBBHUS Det ÃƒÂ¤r Lauras fÃƒÂ¶rsta skoldag och Hamtaro fÃƒÂ¶ljer efter henne fÃƒÂ¶r att hÃƒÂ¥lla ett vakande ÃƒÂ¶ga ÃƒÂ¶ver henne. PÃƒÂ¥ skolan trÃƒÂ¤ffar han sina nya kompisar Oxnard och Boss, som presenterar honom fÃƒÂ¶r flera hamsterkompisar. Hamtaro klÃƒÂ¤cker idÃƒÂ©n att de ska anvÃƒÂ¤nda Boss gÃƒÂ¶mstÃƒÂ¤lle som klubbhus fÃƒÂ¶r en Ham-ham-klubb och det tycker alla ÃƒÂ¤r toppen! PÃƒÂ¥ kvÃƒÂ¤llen, nÃƒÂ¤r Laura berÃƒÂ¤ttar att hennes nya kompisar ocksÃƒÂ¥ har hamstrar, vet Hamtaro att han sÃƒÂ¤kert kommer att trÃƒÂ¤ffa dem i det nya Ham-ham-klubbhuset! ","torrent":{"xt":"urn:btih:7198de6a943c7d43d1d4071aba7ae121ac3efaf9","amp;dn":"Hamtaro.och.ham.ham.klubbhuset.swedish.ispy100fib","amp;tr":["udp%3A%2F%2Ftracker.openbittorrent.com%3A80","udp%3A%2F%2Fopen.demonii.com%3A1337","udp%3A%2F%2Ftracker.coppersurfer.tk%3A6969","udp%3A%2F%2Fexodus.desync.com%3A6969"],"infoHash":"7198de6a943c7d43d1d4071aba7ae121ac3efaf9","infoHashBuffer":{"type":"Buffer","data":[113,152,222,106,148,60,125,67,209,212,7,26,186,122,225,33,172,62,250,249]},"announce":[],"urlList":[]}}