{"title":"Spider-Island - Cloak and Dagger (01 - 03) (2011) (digital) (Min","uid":11512083,"size":135947736,"categoryP":"other","categoryS":"comics","magnet":"?xt=urn:btih:7a1bb30c23c4e3b10b59e00b0eb0bceccdd0c4d8&amp;dn=Spider-Island+-+Cloak+and+Dagger+%2801+-+03%29+%282011%29+%28digital%29+%28Min&amp;tr=udp%3A%2F%2Ftracker.openbittorrent.com%3A80&amp;tr=udp%3A%2F%2Fopen.demonii.com%3A1337&amp;tr=udp%3A%2F%2Ftracker.coppersurfer.tk%3A6969&amp;tr=udp%3A%2F%2Fexodus.desync.com%3A6969","seeders":0,"leechers":1,"uploader":"nemesis43","files":3,"time":1416410088,"description":"Spider-Island - Cloak and Dagger (01 - 03) (2011) (digital) (Minutemen-Faessla)","torrent":{"xt":"urn:btih:7a1bb30c23c4e3b10b59e00b0eb0bceccdd0c4d8","amp;dn":"Spider-Island+-+Cloak+and+Dagger+%2801+-+03%29+%282011%29+%28digital%29+%28Min","amp;tr":["udp%3A%2F%2Ftracker.openbittorrent.com%3A80","udp%3A%2F%2Fopen.demonii.com%3A1337","udp%3A%2F%2Ftracker.coppersurfer.tk%3A6969","udp%3A%2F%2Fexodus.desync.com%3A6969"],"infoHash":"7a1bb30c23c4e3b10b59e00b0eb0bceccdd0c4d8","infoHashBuffer":{"type":"Buffer","data":[122,27,179,12,35,196,227,177,11,89,224,11,14,176,188,236,205,208,196,216]},"announce":[],"urlList":[]}}