{"title":"RBD - Tu Amor","uid":4834322,"size":137680900,"categoryP":"video","categoryS":"music_videos","magnet":"?xt=urn:btih:84c50278d6eeed001a53a55408614fe141ef6b07&amp;dn=RBD+-+Tu+Amor&amp;tr=udp%3A%2F%2Ftracker.openbittorrent.com%3A80&amp;tr=udp%3A%2F%2Fopen.demonii.com%3A1337&amp;tr=udp%3A%2F%2Ftracker.coppersurfer.tk%3A6969&amp;tr=udp%3A%2F%2Fexodus.desync.com%3A6969","seeders":0,"leechers":1,"uploader":"2nafish","files":-1,"time":1239256516,"description":"Source: TV\n\nFile Info:\n\nVideo: MPEG-2 video , 720x480, 29.97 fps, VBR (Constant quality), Maximum 6124 Kb/s\nAudio: Dolby Digital, 48000 Hz, Stereo, 256 kbps\n\n\n&quot;Tu amor&quot; (English: &quot;Your Love&quot;) is the first single released from RBD's fourth studio and first all-English album, Rebels.\n\nThe video for &quot;Tu Amor&quot; was shot on the beach in Los Angeles. MTV Tr3s premiered it on October 23, 2006 and it made its debut at number 6 on Mi TRL, aired on MTV Tr3s. The video also airs on MTV Hits. The video shows them on the beach having fun, and also having a bonfire. Fans noticed that there were only solo shots of Christopher in the video, not being shown with the others. This was due the fact he was not there when the rest of the group were shooting the video. His scenes were filmed later and included in the video.\n\nThe lead vocals are sung by Christian Chavez. This single is a cover of a song originally released in 1997 by Jon B, included in his album Cool Relax. Tu amor won the 'La chanson internationale de l'annÃƒÂ©e' (International Song of the year) from Cherie FM Les Etoiles, a popular radio station in France.\n\n&quot;Tu Amor&quot; debuted on On-Air With Ryan Seacrest morning show on KIIS-FM in Los Angeles.\n\nAccording to writer Diane Warren and Media Base, the song was released to American radio on September 22, 2006. According to AMG, the single was released on CD in the United States on November 24, 2006.\n\n\nMy Videos:\n &lt;a href=&quot;\nhttp://thepiratebay.se/user/2nafish/&quot; rel=&quot;nofollow&quot; target=&quot;_NEW&quot;&gt;\nhttp://thepiratebay.se/user/2nafish/&lt;/a&gt;","torrent":{"xt":"urn:btih:84c50278d6eeed001a53a55408614fe141ef6b07","amp;dn":"RBD+-+Tu+Amor","amp;tr":["udp%3A%2F%2Ftracker.openbittorrent.com%3A80","udp%3A%2F%2Fopen.demonii.com%3A1337","udp%3A%2F%2Ftracker.coppersurfer.tk%3A6969","udp%3A%2F%2Fexodus.desync.com%3A6969"],"infoHash":"84c50278d6eeed001a53a55408614fe141ef6b07","infoHashBuffer":{"type":"Buffer","data":[132,197,2,120,214,238,237,0,26,83,165,84,8,97,79,225,65,239,107,7]},"announce":[],"urlList":[]}}