{"title":"Centurion (2010) PAL Retail DVDR Eng-NLSubs NLUPPER","uid":5756176,"size":4637218846,"categoryP":"video","categoryS":"movies_dvdr","magnet":"?xt=urn:btih:93db8b1bf957b5777a7f4b05a1dcf69e03fc43fe&amp;dn=Centurion+%282010%29+PAL+Retail+DVDR+Eng-NLSubs+NLUPPER&amp;tr=udp%3A%2F%2Ftracker.openbittorrent.com%3A80&amp;tr=udp%3A%2F%2Fopen.demonii.com%3A1337&amp;tr=udp%3A%2F%2Ftracker.coppersurfer.tk%3A6969&amp;tr=udp%3A%2F%2Fexodus.desync.com%3A6969","seeders":0,"leechers":1,"uploader":"NLUPPER002","files":-1,"time":1281568617,"description":"Centurion (2010) PAL Retail DVDR Eng-NLSubs NLUPPER\n\nMM:   &lt;a href=&quot; http://www.moviemeter.nl/film/56751&quot; rel=&quot;nofollow&quot; target=&quot;_NEW&quot;&gt; http://www.moviemeter.nl/film/56751&lt;/a&gt;\n\nIMDB:   &lt;a href=&quot; http://www.imdb.com/title/tt1020558/&quot; rel=&quot;nofollow&quot; target=&quot;_NEW&quot;&gt; http://www.imdb.com/title/tt1020558/&lt;/a&gt;\n\nINFO\n\nMovie...........: Centurion (2010)\nRuntime.........: 97 minuten\nFormat..........: DVDR\nSource..........: Centurion.LiMiTED.PAL.DVDR-ALLiANCE\nMain Movie .....: CCE6 @ 5971Kbs\nAudio ..........: Engels AC3 DD5.1\nMenu ...........: Ja, aangepast waar nodig\nEdited by ......: Jodinho, thanx m8\nSubtitles ......: English Retail Dutch custom by Tokke &amp; Heksje, weer een hele mooie team!\nControle........: Tokke\nBewerking&amp;Resync: Tokke, thanx m8 erg goed werk!\n","torrent":{"xt":"urn:btih:93db8b1bf957b5777a7f4b05a1dcf69e03fc43fe","amp;dn":"Centurion+%282010%29+PAL+Retail+DVDR+Eng-NLSubs+NLUPPER","amp;tr":["udp%3A%2F%2Ftracker.openbittorrent.com%3A80","udp%3A%2F%2Fopen.demonii.com%3A1337","udp%3A%2F%2Ftracker.coppersurfer.tk%3A6969","udp%3A%2F%2Fexodus.desync.com%3A6969"],"infoHash":"93db8b1bf957b5777a7f4b05a1dcf69e03fc43fe","infoHashBuffer":{"type":"Buffer","data":[147,219,139,27,249,87,181,119,122,127,75,5,161,220,246,158,3,252,67,254]},"announce":[],"urlList":[]}}