{"title":"SHAREGO-PRONripz-SLUTTYSQUIRTERS-TINY TITS-AUBREY","uid":4513038,"size":40551387,"categoryP":"porn","categoryS":"movie_clips","magnet":"?xt=urn:btih:a4b26dbd7d24ae1380bad1c3d6136c5831afd0aa&amp;dn=SHAREGO-PRONripz-SLUTTYSQUIRTERS-TINY+TITS-AUBREY&amp;tr=udp%3A%2F%2Ftracker.openbittorrent.com%3A80&amp;tr=udp%3A%2F%2Fopen.demonii.com%3A1337&amp;tr=udp%3A%2F%2Ftracker.coppersurfer.tk%3A6969&amp;tr=udp%3A%2F%2Fexodus.desync.com%3A6969","seeders":0,"leechers":1,"uploader":"dodgerblue","files":6,"time":1226861341,"description":"\nSHAREGO-PRONripz-SLUTTYSQUIRTERS-TINY TITS-AUBREY\nFORMAT WMV 38.7 MB\nAubrey is bored and horny, and ready to for you. Her pussy is juicy, pink, and ready for some hot action. This time things may have gotten a little too hot, her pussy couldn&amp;#039;t resist to unleash a fountain just for you. \n","torrent":{"xt":"urn:btih:a4b26dbd7d24ae1380bad1c3d6136c5831afd0aa","amp;dn":"SHAREGO-PRONripz-SLUTTYSQUIRTERS-TINY+TITS-AUBREY","amp;tr":["udp%3A%2F%2Ftracker.openbittorrent.com%3A80","udp%3A%2F%2Fopen.demonii.com%3A1337","udp%3A%2F%2Ftracker.coppersurfer.tk%3A6969","udp%3A%2F%2Fexodus.desync.com%3A6969"],"infoHash":"a4b26dbd7d24ae1380bad1c3d6136c5831afd0aa","infoHashBuffer":{"type":"Buffer","data":[164,178,109,189,125,36,174,19,128,186,209,195,214,19,108,88,49,175,208,170]},"announce":[],"urlList":[]}}