{"title":"UCO.Unidad.Central.Operativa.2x03.2009.SPANISH.DSR.XviD.[oSeries","uid":4953103,"size":671111168,"categoryP":"video","categoryS":"tv_shows","magnet":"?xt=urn:btih:c98a0cabae465565a822c46c79d3096713a52eef&amp;dn=UCO.Unidad.Central.Operativa.2x03.2009.SPANISH.DSR.XviD.%5BoSeries&amp;tr=udp%3A%2F%2Ftracker.openbittorrent.com%3A80&amp;tr=udp%3A%2F%2Fopen.demonii.com%3A1337&amp;tr=udp%3A%2F%2Ftracker.coppersurfer.tk%3A6969&amp;tr=udp%3A%2F%2Fexodus.desync.com%3A6969","seeders":0,"leechers":0,"uploader":"gamolama","files":1,"time":1244985858,"description":"UCO.Unidad.Central.Operativa.2x03.2009.SPANISH.DSR.XviD.[oSeries.com]","torrent":{"xt":"urn:btih:c98a0cabae465565a822c46c79d3096713a52eef","amp;dn":"UCO.Unidad.Central.Operativa.2x03.2009.SPANISH.DSR.XviD.%5BoSeries","amp;tr":["udp%3A%2F%2Ftracker.openbittorrent.com%3A80","udp%3A%2F%2Fopen.demonii.com%3A1337","udp%3A%2F%2Ftracker.coppersurfer.tk%3A6969","udp%3A%2F%2Fexodus.desync.com%3A6969"],"infoHash":"c98a0cabae465565a822c46c79d3096713a52eef","infoHashBuffer":{"type":"Buffer","data":[201,138,12,171,174,70,85,101,168,34,196,108,121,211,9,103,19,165,46,239]},"announce":[],"urlList":[]}}