{"title":"Mommy.Got.Boobs.-.Holly.Halston","uid":5766928,"size":622721366,"categoryP":"porn","categoryS":"movie_clips","magnet":"?xt=urn:btih:cd8a0ff9be9eaee5eb746324ec2b8eb394b5a457&amp;dn=Mommy.Got.Boobs.-.Holly.Halston&amp;tr=udp%3A%2F%2Ftracker.openbittorrent.com%3A80&amp;tr=udp%3A%2F%2Fopen.demonii.com%3A1337&amp;tr=udp%3A%2F%2Ftracker.coppersurfer.tk%3A6969&amp;tr=udp%3A%2F%2Fexodus.desync.com%3A6969","seeders":0,"leechers":0,"uploader":"Rabiner","files":4,"time":1281948052,"description":"Mommy.Got.Boobs.-.Holly.Halston\n\n\n &lt;a href=&quot;\nhttp://www.imagefruit.com/img/2694/1.jpg&quot; rel=&quot;nofollow&quot; target=&quot;_NEW&quot;&gt;\nhttp://www.imagefruit.com/img/2694/1.jpg&lt;/a&gt;","torrent":{"xt":"urn:btih:cd8a0ff9be9eaee5eb746324ec2b8eb394b5a457","amp;dn":"Mommy.Got.Boobs.-.Holly.Halston","amp;tr":["udp%3A%2F%2Ftracker.openbittorrent.com%3A80","udp%3A%2F%2Fopen.demonii.com%3A1337","udp%3A%2F%2Ftracker.coppersurfer.tk%3A6969","udp%3A%2F%2Fexodus.desync.com%3A6969"],"infoHash":"cd8a0ff9be9eaee5eb746324ec2b8eb394b5a457","infoHashBuffer":{"type":"Buffer","data":[205,138,15,249,190,158,174,229,235,116,99,36,236,43,142,179,148,181,164,87]},"announce":[],"urlList":[]}}