{"title":"Wanna.Fuck.My.Daughter.Gotta.Fuck.Me.First.2.XXX.DVDRip.XviD-PLE","uid":9651472,"size":1466456653,"categoryP":"porn","categoryS":"movies","magnet":"?xt=urn:btih:d0f90c49469d9d43b7339a8a96d674a5f1fdefd5&amp;dn=Wanna.Fuck.My.Daughter.Gotta.Fuck.Me.First.2.XXX.DVDRip.XviD-PLE&amp;tr=udp%3A%2F%2Ftracker.openbittorrent.com%3A80&amp;tr=udp%3A%2F%2Fopen.demonii.com%3A1337&amp;tr=udp%3A%2F%2Ftracker.coppersurfer.tk%3A6969&amp;tr=udp%3A%2F%2Fexodus.desync.com%3A6969","seeders":0,"leechers":1,"uploader":"xxxlavalxxx","files":4,"time":1393081657,"description":"Relax. This isn't as hard as you might think. OK, you want to fuck the hottie. What if mom's a hottie too? You can handle fucking mom up the ass for a shot at the fresh pink, right?\nIt wasn't easy, lying in bed with my fingers deep inside my hot, throbbing pussy, while my daughter brought home all her horny new friends, &quot;Enough!&quot;, I said! Then I told her that I needed some heavy screwing too, so from now on all those studs of hers have to pump their first loads in ME!\nAfter all, us moms need it just as bad as our daughters do! Mmmmm, my snatch is getting so wet! I can't wait to suck on some cock, and I just might let my daughter lick my pussy. Surely that will make her boyfriends cum all over us!\n\nCast: Nicole Moore, Sheila Marie, Elli Foxx, Cala Craves, Desi Foxx, Leenuh Rae, Hayden Night, Hannah Santana\n\n\nscreens\n &lt;a href=&quot;\nhttp://imgdone.com/viewer.php?file=63937467312696119398.jpeg&quot; rel=&quot;nofollow&quot; target=&quot;_NEW&quot;&gt;\nhttp://imgdone.com/viewer.php?file=63937467312696119398.jpeg&lt;/a&gt;\n &lt;a href=&quot;\nhttp://imgdone.com/viewer.php?file=74597488168124332662.jpeg&quot; rel=&quot;nofollow&quot; target=&quot;_NEW&quot;&gt;\nhttp://imgdone.com/viewer.php?file=74597488168124332662.jpeg&lt;/a&gt;","torrent":{"xt":"urn:btih:d0f90c49469d9d43b7339a8a96d674a5f1fdefd5","amp;dn":"Wanna.Fuck.My.Daughter.Gotta.Fuck.Me.First.2.XXX.DVDRip.XviD-PLE","amp;tr":["udp%3A%2F%2Ftracker.openbittorrent.com%3A80","udp%3A%2F%2Fopen.demonii.com%3A1337","udp%3A%2F%2Ftracker.coppersurfer.tk%3A6969","udp%3A%2F%2Fexodus.desync.com%3A6969"],"infoHash":"d0f90c49469d9d43b7339a8a96d674a5f1fdefd5","infoHashBuffer":{"type":"Buffer","data":[208,249,12,73,70,157,157,67,183,51,154,138,150,214,116,165,241,253,239,213]},"announce":[],"urlList":[]}}