{"title":"Schoolgirls On Fire 2 2008 XXX","uid":4284944,"size":117403190,"categoryP":"porn","categoryS":"movie_clips","magnet":"?xt=urn:btih:d1ff6b30ebf176c5d65317bdf2ce247a2e60303f&amp;dn=Schoolgirls+On+Fire+2+2008+XXX&amp;tr=udp%3A%2F%2Ftracker.openbittorrent.com%3A80&amp;tr=udp%3A%2F%2Fopen.demonii.com%3A1337&amp;tr=udp%3A%2F%2Ftracker.coppersurfer.tk%3A6969&amp;tr=udp%3A%2F%2Fexodus.desync.com%3A6969","seeders":0,"leechers":0,"uploader":"man0907","files":1,"time":1215639104,"description":"Schoolgirls On Fire 2 2008 XXX","torrent":{"xt":"urn:btih:d1ff6b30ebf176c5d65317bdf2ce247a2e60303f","amp;dn":"Schoolgirls+On+Fire+2+2008+XXX","amp;tr":["udp%3A%2F%2Ftracker.openbittorrent.com%3A80","udp%3A%2F%2Fopen.demonii.com%3A1337","udp%3A%2F%2Ftracker.coppersurfer.tk%3A6969","udp%3A%2F%2Fexodus.desync.com%3A6969"],"infoHash":"d1ff6b30ebf176c5d65317bdf2ce247a2e60303f","infoHashBuffer":{"type":"Buffer","data":[209,255,107,48,235,241,118,197,214,83,23,189,242,206,36,122,46,96,48,63]},"announce":[],"urlList":[]}}