{"title":"Ison &amp; Fille - Galen.mp3","uid":6462735,"size":7506560,"categoryP":"audio","categoryS":"music","magnet":"?xt=urn:btih:d57096087a1cda0dd5ba3548f9e0b7a04b0c5490&amp;dn=Ison+%26+Fille+-+Galen.mp3&amp;tr=udp%3A%2F%2Ftracker.openbittorrent.com%3A80&amp;tr=udp%3A%2F%2Fopen.demonii.com%3A1337&amp;tr=udp%3A%2F%2Ftracker.coppersurfer.tk%3A6969&amp;tr=udp%3A%2F%2Fexodus.desync.com%3A6969","seeders":0,"leechers":0,"uploader":"Worm_TG","files":-1,"time":1307836720,"description":"\nIson &amp; Fille Ft Daniel Adams-Ray singel: Galen 2011\n\n\n\n\nArtist..............:Ison &amp; Fille\nSong Track..........:Galen\nIMG Size............:7.15 Mb\nBitrate.............:310kbit/s\nGenre...............:Hip-Hop\nRelease date........:04-05-2011\nLanguage............:Swedish\n\n\nSeed this!","torrent":{"xt":"urn:btih:d57096087a1cda0dd5ba3548f9e0b7a04b0c5490","amp;dn":"Ison+%26+Fille+-+Galen.mp3","amp;tr":["udp%3A%2F%2Ftracker.openbittorrent.com%3A80","udp%3A%2F%2Fopen.demonii.com%3A1337","udp%3A%2F%2Ftracker.coppersurfer.tk%3A6969","udp%3A%2F%2Fexodus.desync.com%3A6969"],"infoHash":"d57096087a1cda0dd5ba3548f9e0b7a04b0c5490","infoHashBuffer":{"type":"Buffer","data":[213,112,150,8,122,28,218,13,213,186,53,72,249,224,183,160,75,12,84,144]},"announce":[],"urlList":[]}}