{"title":"Plop.en.het.Viool.Avontuur[2006]DvDrip[Eng]-CIA","uid":3963154,"size":734007296,"categoryP":"video","categoryS":"movies","magnet":"?xt=urn:btih:d781f63c479fa6caf2b772f2584ef620fdb86eef&amp;dn=Plop.en.het.Viool.Avontuur%5B2006%5DDvDrip%5BEng%5D-CIA&amp;tr=udp%3A%2F%2Ftracker.openbittorrent.com%3A80&amp;tr=udp%3A%2F%2Fopen.demonii.com%3A1337&amp;tr=udp%3A%2F%2Ftracker.coppersurfer.tk%3A6969&amp;tr=udp%3A%2F%2Fexodus.desync.com%3A6969","seeders":0,"leechers":1,"uploader":"DJ_CIA","files":2,"time":1199570190,"description":"Plop, Klus, Lui and Kwebbel are gathering berries in the forest. Suddenly they hear violin music, which Plop tells must be from the big people living at the edge of the forest, and we see a young girl (granddaughter of a famous female violin player) practicing, with her father nervous for the performance for the audience for the centennial anniversary of her school. Lui goes with Klus to watch the violin itself.","torrent":{"xt":"urn:btih:d781f63c479fa6caf2b772f2584ef620fdb86eef","amp;dn":"Plop.en.het.Viool.Avontuur%5B2006%5DDvDrip%5BEng%5D-CIA","amp;tr":["udp%3A%2F%2Ftracker.openbittorrent.com%3A80","udp%3A%2F%2Fopen.demonii.com%3A1337","udp%3A%2F%2Ftracker.coppersurfer.tk%3A6969","udp%3A%2F%2Fexodus.desync.com%3A6969"],"infoHash":"d781f63c479fa6caf2b772f2584ef620fdb86eef","infoHashBuffer":{"type":"Buffer","data":[215,129,246,60,71,159,166,202,242,183,114,242,88,78,246,32,253,184,110,239]},"announce":[],"urlList":[]}}