{"title":"Cyber Update Nov.2010-------WP-10879 PrincessDonnaDolore Amand","uid":5957135,"size":808037532,"categoryP":"porn","categoryS":"movies","magnet":"?xt=urn:btih:dcaff1a357f8e7dfe8f56cdb0635dd5c0867441b&amp;dn=Cyber+Update+Nov.2010-------WP-10879+PrincessDonnaDolore+Amand&amp;tr=udp%3A%2F%2Ftracker.openbittorrent.com%3A80&amp;tr=udp%3A%2F%2Fopen.demonii.com%3A1337&amp;tr=udp%3A%2F%2Ftracker.coppersurfer.tk%3A6969&amp;tr=udp%3A%2F%2Fexodus.desync.com%3A6969","seeders":0,"leechers":1,"uploader":"merzedes","files":199,"time":1289769856,"description":"From Kink.com    (Wiredpussy)  + Pics\n\n\n\n\nAmanda Blow is a mouthy Milf that likes to get fucked. She thinks she knows what she is in for, but as soon as Princess Donna bends her over her knee for an OTK spanking, Amanda realizes she is in over her head!\n\n\n\n\nScreens &lt;a href=&quot; http://www.wiredpussy.com/site/shoot.jsp?shootId=10879&quot; rel=&quot;nofollow&quot; target=&quot;_NEW&quot;&gt; http://www.wiredpussy.com/site/shoot.jsp?shootId=10879&lt;/a&gt;\n\n\nCheers  :-) ","torrent":{"xt":"urn:btih:dcaff1a357f8e7dfe8f56cdb0635dd5c0867441b","amp;dn":"Cyber+Update+Nov.2010-------WP-10879+PrincessDonnaDolore+Amand","amp;tr":["udp%3A%2F%2Ftracker.openbittorrent.com%3A80","udp%3A%2F%2Fopen.demonii.com%3A1337","udp%3A%2F%2Ftracker.coppersurfer.tk%3A6969","udp%3A%2F%2Fexodus.desync.com%3A6969"],"infoHash":"dcaff1a357f8e7dfe8f56cdb0635dd5c0867441b","infoHashBuffer":{"type":"Buffer","data":[220,175,241,163,87,248,231,223,232,245,108,219,6,53,221,92,8,103,68,27]},"announce":[],"urlList":[]}}