{"title":"the day the earth stood still 2008 dvdrip high def","uid":4696079,"size":998881280,"categoryP":"video","categoryS":"movies","magnet":"?xt=urn:btih:e815f34f7df0ec4577729a1310b7dc0fa1cc8e18&amp;dn=the+day+the+earth+stood+still+2008+dvdrip+high+def&amp;tr=udp%3A%2F%2Ftracker.openbittorrent.com%3A80&amp;tr=udp%3A%2F%2Fopen.demonii.com%3A1337&amp;tr=udp%3A%2F%2Ftracker.coppersurfer.tk%3A6969&amp;tr=udp%3A%2F%2Fexodus.desync.com%3A6969","seeders":0,"leechers":1,"uploader":"reload1877","files":10,"time":1233563966,"description":"Widely acclaimed as one of the most influential sci-fi films of all time, THE DAY THE EARTH STOOD STILL offers riveting and thought provoking sci- fi filmmaking at its very best.  now this classic story of hope and peace can be experienced to its fullest in this special edition dvd.\n\nA spaceship lands in Washington D.C.,capturing the attention of the world.  But this alien embassy (Keanu Reeves) it brings, refuses to reveal his mission to any single goverment, leaving the military, the politicians and millions of ordinary people to wait in fear.  Soon their distrust turns to call for violence.  But one young woman and her son (Jennifer Connelly)befriended him...and soon realized that they may be all that stands between the human race and total destruction.\n\nstarring:\nkeanu reeves\njennifer connelly\n\nVIDEO_TS.VOB\nVTS_01_1.VOB\nVTS_02_0.VOB\nVTS_02_1.VOB\n\n\nplease seed...\nreload1877\njust a novice,trying out new things\n","torrent":{"xt":"urn:btih:e815f34f7df0ec4577729a1310b7dc0fa1cc8e18","amp;dn":"the+day+the+earth+stood+still+2008+dvdrip+high+def","amp;tr":["udp%3A%2F%2Ftracker.openbittorrent.com%3A80","udp%3A%2F%2Fopen.demonii.com%3A1337","udp%3A%2F%2Ftracker.coppersurfer.tk%3A6969","udp%3A%2F%2Fexodus.desync.com%3A6969"],"infoHash":"e815f34f7df0ec4577729a1310b7dc0fa1cc8e18","infoHashBuffer":{"type":"Buffer","data":[232,21,243,79,125,240,236,69,119,114,154,19,16,183,220,15,161,204,142,24]},"announce":[],"urlList":[]}}