{"title":"Veruca James - Lie Dicktector","uid":11221265,"size":413980731,"categoryP":"porn","categoryS":"movie_clips","magnet":"?xt=urn:btih:ec6a7c6e34309e4b13acdfdd70680f14636a1ad2&amp;dn=Veruca+James+-+Lie+Dicktector&amp;tr=udp%3A%2F%2Ftracker.openbittorrent.com%3A80&amp;tr=udp%3A%2F%2Fopen.demonii.com%3A1337&amp;tr=udp%3A%2F%2Ftracker.coppersurfer.tk%3A6969&amp;tr=udp%3A%2F%2Fexodus.desync.com%3A6969","seeders":0,"leechers":1,"uploader":"ElitePorn","files":-1,"time":1413387759,"description":"Veruca James - Lie Dicktector\n-----------------------------\n\nScreenshots:\n------------\n &lt;a href=&quot;\nhttp://picturescream.asia/soft/wqI&quot; rel=&quot;nofollow&quot; target=&quot;_NEW&quot;&gt;\nhttp://picturescream.asia/soft/wqI&lt;/a&gt;\n &lt;a href=&quot;\nhttp://picturescream.asia/soft/wqt&quot; rel=&quot;nofollow&quot; target=&quot;_NEW&quot;&gt;\nhttp://picturescream.asia/soft/wqt&lt;/a&gt;\n &lt;a href=&quot;\nhttp://picturescream.asia/soft/wq2&quot; rel=&quot;nofollow&quot; target=&quot;_NEW&quot;&gt;\nhttp://picturescream.asia/soft/wq2&lt;/a&gt;\n &lt;a href=&quot;\nhttp://picturescream.asia/soft/wqJ&quot; rel=&quot;nofollow&quot; target=&quot;_NEW&quot;&gt;\nhttp://picturescream.asia/soft/wqJ&lt;/a&gt;\n &lt;a href=&quot;\nhttp://picturescream.asia/soft/wqK&quot; rel=&quot;nofollow&quot; target=&quot;_NEW&quot;&gt;\nhttp://picturescream.asia/soft/wqK&lt;/a&gt;\n &lt;a href=&quot;\nhttp://picturescream.asia/soft/wqW&quot; rel=&quot;nofollow&quot; target=&quot;_NEW&quot;&gt;\nhttp://picturescream.asia/soft/wqW&lt;/a&gt;\n &lt;a href=&quot;\nhttp://picturescream.asia/soft/wqf&quot; rel=&quot;nofollow&quot; target=&quot;_NEW&quot;&gt;\nhttp://picturescream.asia/soft/wqf&lt;/a&gt;\n &lt;a href=&quot;\nhttp://picturescream.asia/soft/wqz&quot; rel=&quot;nofollow&quot; target=&quot;_NEW&quot;&gt;\nhttp://picturescream.asia/soft/wqz&lt;/a&gt;\n &lt;a href=&quot;\nhttp://picturescream.asia/soft/wqR&quot; rel=&quot;nofollow&quot; target=&quot;_NEW&quot;&gt;\nhttp://picturescream.asia/soft/wqR&lt;/a&gt;\n\n\nDuration: 46:40, Format: MP4, Resolution: 854x480, Size: 394.80 MB","torrent":{"xt":"urn:btih:ec6a7c6e34309e4b13acdfdd70680f14636a1ad2","amp;dn":"Veruca+James+-+Lie+Dicktector","amp;tr":["udp%3A%2F%2Ftracker.openbittorrent.com%3A80","udp%3A%2F%2Fopen.demonii.com%3A1337","udp%3A%2F%2Ftracker.coppersurfer.tk%3A6969","udp%3A%2F%2Fexodus.desync.com%3A6969"],"infoHash":"ec6a7c6e34309e4b13acdfdd70680f14636a1ad2","infoHashBuffer":{"type":"Buffer","data":[236,106,124,110,52,48,158,75,19,172,223,221,112,104,15,20,99,106,26,210]},"announce":[],"urlList":[]}}