{"title":"Adrian Receanu (fluier,caval si clarinet) - Tezaur folcloric mol","uid":4785679,"size":32108901,"categoryP":"audio","categoryS":"other","magnet":"?xt=urn:btih:f12440680650341268c5347385685de116c107c8&amp;dn=Adrian+Receanu+%28fluier%2Ccaval+si+clarinet%29+-+Tezaur+folcloric+mol&amp;tr=udp%3A%2F%2Ftracker.openbittorrent.com%3A80&amp;tr=udp%3A%2F%2Fopen.demonii.com%3A1337&amp;tr=udp%3A%2F%2Ftracker.coppersurfer.tk%3A6969&amp;tr=udp%3A%2F%2Fexodus.desync.com%3A6969","seeders":0,"leechers":1,"uploader":"ill88eagle","files":-1,"time":1237545695,"description":"Melodii cantate la fluier,caval si clarinet \nBitrate 128 kbps \n27 Mb \n\n01. Sarba (2:47) \n02. Melodie de ascultare (2:42) \n03. Ca la cimpoi (1:33) \n04. Doina-nsingurarii (2:14) \n05. Amintiri oltenesti (1:34) \n06. Sarba de concert (2:09) \n07. Hora ca la sud (1:29) \n08. Hora glodenenilor (2:42) \n09. Colo-n vale... (2:21) \n10. Tatal meu, ce esti departe (2:38) \n11. Polca lui Botnari (1:39) \n12. Foaie verde maghiran (2:01) \n13. Batuta moldoveneasca (1:16) \n14. O hora lautareasca (1:46) \n","torrent":{"xt":"urn:btih:f12440680650341268c5347385685de116c107c8","amp;dn":"Adrian+Receanu+%28fluier%2Ccaval+si+clarinet%29+-+Tezaur+folcloric+mol","amp;tr":["udp%3A%2F%2Ftracker.openbittorrent.com%3A80","udp%3A%2F%2Fopen.demonii.com%3A1337","udp%3A%2F%2Ftracker.coppersurfer.tk%3A6969","udp%3A%2F%2Fexodus.desync.com%3A6969"],"infoHash":"f12440680650341268c5347385685de116c107c8","infoHashBuffer":{"type":"Buffer","data":[241,36,64,104,6,80,52,18,104,197,52,115,133,104,93,225,22,193,7,200]},"announce":[],"urlList":[]}}