{"title":"True Ex-GF Amateur - Patrina B. - 084","uid":9425167,"size":11907990,"categoryP":"porn","categoryS":"pictures","magnet":"?xt=urn:btih:f376e6ea1f8ac9e0f43ded8e345b9b9b151fd98f&amp;dn=True+Ex-GF+Amateur+-+Patrina+B.+-+084&amp;tr=udp%3A%2F%2Ftracker.openbittorrent.com%3A80&amp;tr=udp%3A%2F%2Fopen.demonii.com%3A1337&amp;tr=udp%3A%2F%2Ftracker.coppersurfer.tk%3A6969&amp;tr=udp%3A%2F%2Fexodus.desync.com%3A6969","seeders":0,"leechers":0,"uploader":null,"files":94,"time":1388674330,"description":"Complete / Full Amateur Amateur Ex-Girlfriend Set.\n\n\nSamples are SFW, Full Set is NSFW. Mostly topless shots. \n\n\n\nSamples:\n &lt;a href=&quot;\nhttp://easyimghost.com/ImageHosting/14352_0022.jpg.html&quot; rel=&quot;nofollow&quot; target=&quot;_NEW&quot;&gt;\nhttp://easyimghost.com/ImageHosting/14352_0022.jpg.html&lt;/a&gt; \n &lt;a href=&quot;\nhttp://easyimghost.com/ImageHosting/14353_0070.jpg.html&quot; rel=&quot;nofollow&quot; target=&quot;_NEW&quot;&gt;\nhttp://easyimghost.com/ImageHosting/14353_0070.jpg.html&lt;/a&gt; ","torrent":{"xt":"urn:btih:f376e6ea1f8ac9e0f43ded8e345b9b9b151fd98f","amp;dn":"True+Ex-GF+Amateur+-+Patrina+B.+-+084","amp;tr":["udp%3A%2F%2Ftracker.openbittorrent.com%3A80","udp%3A%2F%2Fopen.demonii.com%3A1337","udp%3A%2F%2Ftracker.coppersurfer.tk%3A6969","udp%3A%2F%2Fexodus.desync.com%3A6969"],"infoHash":"f376e6ea1f8ac9e0f43ded8e345b9b9b151fd98f","infoHashBuffer":{"type":"Buffer","data":[243,118,230,234,31,138,201,224,244,61,237,142,52,91,155,155,21,31,217,143]},"announce":[],"urlList":[]}}